README.md
setup.py
GPGO/Acquisition.py
GPGO/Opt.py
GPGO/Opt_old.py
GPGO/__init__.py
GPGO/dpd_opt_script.py
GPGO.egg-info/PKG-INFO
GPGO.egg-info/SOURCES.txt
GPGO.egg-info/dependency_links.txt
GPGO.egg-info/requires.txt
GPGO.egg-info/top_level.txt
GPGO/GaussianProcess/GP.py
GPGO/GaussianProcess/Plotting.py
GPGO/GaussianProcess/__init__.py
GPGO/GaussianProcess/util.py
GPGO/GaussianProcess/Kernel/Kernel.py
GPGO/GaussianProcess/Kernel/Matern.py
GPGO/GaussianProcess/Kernel/RBF.py
GPGO/GaussianProcess/Kernel/__init__.py