Metadata-Version: 2.1
Name: GPGO
Version: 0.1.2
Summary: Bayesian Optimization with Gaussian Process as surrogate model
Home-page: https://github.com/FNTwin/GPGO
Author: Cristian Gabellini
License: MIT
Download-URL: https://github.com/FNTwin/GPGO/archive/0.1.2.tar.gz
Platform: UNKNOWN
Classifier: Development Status :: 3 - Alpha
Classifier: Intended Audience :: Developers
Classifier: Topic :: Software Development :: Build Tools
Classifier: License :: OSI Approved :: MIT License
Classifier: Programming Language :: Python :: 3.6
Requires-Python: >=3.6
Provides-Extra: DIRECT
Provides-Extra: all
Provides-Extra: smt
